archive_path/__init__.py
archive_path/common.py
archive_path/py.typed
archive_path/tar_path.py
archive_path/zip_path.py
archive_path-0.4.2.dist-info/LICENSE
archive_path-0.4.2.dist-info/WHEEL
archive_path-0.4.2.dist-info/METADATA
archive_path-0.4.2.dist-info/RECORD
