Metadata-Version: 2.1
Name: archive-path
Version: 0.4.2
Summary: A package to provide pathlib like access to zip & tar archives.
Home-page: https://github.com/aiidateam/archive-path
Keywords: archive zip tar pathlib
Author: Chris Sewell
Author-email: executablebooks@gmail.com
Requires-Python: >=3.8
Classifier: Intended Audience :: Developers
Classifier: License :: OSI Approved :: MIT License
Classifier: Programming Language :: Python :: 3
Classifier: Programming Language :: Python :: 3.8
Classifier: Programming Language :: Python :: 3.9
Classifier: Programming Language :: Python :: 3.10
Classifier: Programming Language :: Python :: 3.11
Classifier: Topic :: Software Development :: Libraries :: Python Modules
Requires-Dist: pre-commit ; extra == "dev"
Requires-Dist: pytest~=6.0 ; extra == "test"
Requires-Dist: coverage ; extra == "test"
Requires-Dist: pytest-cov ; extra == "test"
Provides-Extra: dev
Provides-Extra: test
